{"symbols":{"GuestsRepository":{"hasNamespace":false,"type":0,"moduleName":"guest.repository","relativePath":"functions/src/guests/guest.repository"},"GuestEntity":{"hasNamespace":false,"type":0,"moduleName":"guest.entity","relativePath":"functions/src/guests/guest.entity"},"GuestsRouter":{"hasNamespace":false,"type":0,"moduleName":"guest.router","relativePath":"functions/src/guests/guest.router"},"GuestsService":{"hasNamespace":false,"type":0,"moduleName":"guest.service","relativePath":"functions/src/guests/guest.service"},"GuestDto":{"hasNamespace":false,"type":0,"moduleName":"guest.dto","relativePath":"functions/src/guests/guest.dto"},"GuestsController":{"hasNamespace":false,"type":0,"moduleName":"guest.controller","relativePath":"functions/src/guests/guest.controller"},"RouterApi":{"hasNamespace":false,"type":0,"moduleName":"index","relativePath":"functions/src/routes/index"},"EventsApi":{"hasNamespace":false,"type":0,"moduleName":"server","relativePath":"functions/src/server"},"EventsController":{"hasNamespace":false,"type":0,"moduleName":"events.controller","relativePath":"functions/src/events/events.controller"},"EventsRouter":{"hasNamespace":false,"type":0,"moduleName":"events.router","relativePath":"functions/src/events/events.router"},"Planner":{"hasNamespace":false,"type":0,"moduleName":"events.entity","relativePath":"functions/src/events/events.entity"},"EventsEntity":{"hasNamespace":false,"type":0,"moduleName":"events.entity","relativePath":"functions/src/events/events.entity"},"EventsService":{"hasNamespace":false,"type":0,"moduleName":"events.service","relativePath":"functions/src/events/events.service"},"EventsDto":{"hasNamespace":false,"type":0,"moduleName":"events.dto","relativePath":"functions/src/events/events.dto"},"EventsRepository":{"hasNamespace":false,"type":0,"moduleName":"events.repository","relativePath":"functions/src/events/events.repository"},"EventsSettingsController":{"hasNamespace":false,"type":0,"moduleName":"eventsSettings.controller","relativePath":"functions/src/eventSettings/eventsSettings.controller"},"EventsSettingsRouter":{"hasNamespace":false,"type":0,"moduleName":"eventsSettings.router","relativePath":"functions/src/eventSettings/eventsSettings.router"},"EventsSettingsDto":{"hasNamespace":false,"type":0,"moduleName":"eventsSettings.dto","relativePath":"functions/src/eventSettings/eventsSettings.dto"},"EventsSettingsService":{"hasNamespace":false,"type":0,"moduleName":"eventsSettings.service","relativePath":"functions/src/eventSettings/eventsSettings.service"},"EventsSettingsRepository":{"hasNamespace":false,"type":0,"moduleName":"eventsSettings.repository","relativePath":"functions/src/eventSettings/eventsSettings.repository"},"EventsSettingsEntity":{"hasNamespace":false,"type":0,"moduleName":"eventsSettings.entity","relativePath":"functions/src/eventSettings/eventsSettings.entity"},"UsersRepository":{"hasNamespace":false,"type":0,"moduleName":"users.repository","relativePath":"functions/src/users/users.repository"},"UsersRouter":{"hasNamespace":false,"type":0,"moduleName":"users.router","relativePath":"functions/src/users/users.router"},"UsersController":{"hasNamespace":false,"type":0,"moduleName":"users.controller","relativePath":"functions/src/users/users.controller"},"UsersService":{"hasNamespace":false,"type":0,"moduleName":"users.service","relativePath":"functions/src/users/users.service"},"UserDto":{"hasNamespace":false,"type":0,"moduleName":"users.dto","relativePath":"functions/src/users/users.dto"},"UsersEntity":{"hasNamespace":false,"type":0,"moduleName":"users.entity","relativePath":"functions/src/users/users.entity"},"UserFlow":{"hasNamespace":false,"type":0,"moduleName":"userflow","relativePath":"functions/src/common/interfaces/userflow"},"BaseRoute":{"hasNamespace":false,"type":1,"moduleName":"baseRoute.interface","relativePath":"functions/src/common/interfaces/baseRoute.interface"},"RequestUser":{"hasNamespace":false,"type":1,"moduleName":"requestUser.interface","relativePath":"functions/src/common/interfaces/requestUser.interface"},"BaseRepository":{"hasNamespace":false,"type":0,"moduleName":"repository.base","relativePath":"functions/src/common/base/repository.base"},"Validator":{"hasNamespace":false,"type":0,"moduleName":"validator.helper","relativePath":"functions/src/common/helpers/validator.helper"},"GeneralError":{"hasNamespace":false,"type":0,"moduleName":"general.error","relativePath":"functions/src/common/errors/general.error"},"BadRequest":{"hasNamespace":false,"type":0,"moduleName":"general.error","relativePath":"functions/src/common/errors/general.error"},"NotFound":{"hasNamespace":false,"type":0,"moduleName":"general.error","relativePath":"functions/src/common/errors/general.error"},"UnAuthorized":{"hasNamespace":false,"type":0,"moduleName":"general.error","relativePath":"functions/src/common/errors/general.error"},"DBError":{"hasNamespace":false,"type":0,"moduleName":"DB.error","relativePath":"functions/src/common/errors/DB.error"},"Forbidden":{"hasNamespace":false,"type":0,"moduleName":"general.error","relativePath":"functions/src/common/errors/general.error"},"ConflictError":{"hasNamespace":false,"type":0,"moduleName":"general.error","relativePath":"functions/src/common/errors/general.error"},"FBAuthMiddleware":{"hasNamespace":false,"type":0,"moduleName":"fbAuth.middleware","relativePath":"functions/src/common/middlewares/fbAuth.middleware"},"BaseDto":{"hasNamespace":false,"type":0,"moduleName":"dto.abstract","relativePath":"functions/src/common/abstract/dto.abstract"},"BaseAbstractRoute":{"hasNamespace":false,"type":0,"moduleName":"route.absrtact","relativePath":"functions/src/common/abstract/route.absrtact"},"BaseEntity":{"hasNamespace":false,"type":0,"moduleName":"entity.abstract","relativePath":"functions/src/common/abstract/entity.abstract"},"TasksEntity":{"hasNamespace":false,"type":0,"moduleName":"tasks.entity","relativePath":"functions/src/taskManager/tasks.entity"},"TasksController":{"hasNamespace":false,"type":0,"moduleName":"tasks.controller","relativePath":"functions/src/taskManager/tasks.controller"},"TasksDto":{"hasNamespace":false,"type":0,"moduleName":"tasks.dto","relativePath":"functions/src/taskManager/tasks.dto"},"TasksService":{"hasNamespace":false,"type":0,"moduleName":"tasks.service","relativePath":"functions/src/taskManager/tasks.service"},"TasksRouter":{"hasNamespace":false,"type":0,"moduleName":"tasks.router","relativePath":"functions/src/taskManager/tasks.router"},"TasksRepository":{"hasNamespace":false,"type":0,"moduleName":"tasks.repository","relativePath":"functions/src/taskManager/tasks.repository"},"TablesController":{"hasNamespace":false,"type":0,"moduleName":"tables.controller","relativePath":"functions/src/tables/tables.controller"},"TablesService":{"hasNamespace":false,"type":0,"moduleName":"tables.service","relativePath":"functions/src/tables/tables.service"},"TablesEntity":{"hasNamespace":false,"type":0,"moduleName":"tables.entity","relativePath":"functions/src/tables/tables.entity"},"TablesRepository":{"hasNamespace":false,"type":0,"moduleName":"tables.repository","relativePath":"functions/src/tables/tables.repository"},"TablesDto":{"hasNamespace":false,"type":0,"moduleName":"tables.dto","relativePath":"functions/src/tables/tables.dto"},"TablesRouter":{"hasNamespace":false,"type":0,"moduleName":"tables.router","relativePath":"functions/src/tables/tables.router"},"GuestsCategoryRepository":{"hasNamespace":false,"type":0,"moduleName":"guestCategories.respository","relativePath":"functions/src/guestCategories/guestCategories.respository"},"GuestsCategoryService":{"hasNamespace":false,"type":0,"moduleName":"GuestsCategory.service","relativePath":"functions/src/guestCategories/GuestsCategory.service"},"GuestsCategoryRouter":{"hasNamespace":false,"type":0,"moduleName":"guestCategories.router","relativePath":"functions/src/guestCategories/guestCategories.router"},"GuestsCategoryController":{"hasNamespace":false,"type":0,"moduleName":"guestCategories.controller","relativePath":"functions/src/guestCategories/guestCategories.controller"},"GuestsCategoryEntity":{"hasNamespace":false,"type":0,"moduleName":"guestCategories.entity","relativePath":"functions/src/guestCategories/guestCategories.entity"}},"files":{"functions/src/guests/guest.repository.ts":"2023-04-11T11:53:49.163Z","functions/src/guests/guest.entity.ts":"2023-04-11T11:53:49.163Z","functions/src/guests/guest.router.ts":"2023-04-11T11:53:49.164Z","functions/src/guests/guest.service.ts":"2023-04-11T11:53:49.164Z","functions/src/guests/guest.dto.ts":"2023-04-11T11:53:49.163Z","functions/src/guests/guest.controller.ts":"2023-04-11T11:53:49.163Z","functions/src/routes/index.ts":"2023-04-11T11:53:49.164Z","functions/src/server.ts":"2023-04-11T12:14:52.402Z","functions/src/events/events.controller.ts":"2023-04-11T11:53:49.162Z","functions/src/events/events.router.ts":"2023-04-11T11:53:49.162Z","functions/src/events/events.entity.ts":"2023-04-11T11:53:49.162Z","functions/src/events/events.service.ts":"2023-04-11T11:53:49.162Z","functions/src/events/events.dto.ts":"2023-04-11T11:53:49.162Z","functions/src/events/events.repository.ts":"2023-04-11T11:53:49.162Z","functions/src/eventSettings/eventsSettings.controller.ts":"2023-04-11T11:53:49.161Z","functions/src/eventSettings/eventsSettings.router.ts":"2023-04-11T11:53:49.161Z","functions/src/eventSettings/eventsSettings.dto.ts":"2023-04-11T11:53:49.161Z","functions/src/eventSettings/eventsSettings.service.ts":"2023-04-11T11:53:49.161Z","functions/src/eventSettings/eventsSettings.repository.ts":"2023-04-11T11:53:49.161Z","functions/src/eventSettings/eventsSettings.entity.ts":"2023-04-11T11:53:49.161Z","functions/src/index.ts":"2023-04-12T20:01:27.993Z","functions/src/users/users.repository.ts":"2023-04-11T11:53:49.166Z","functions/src/users/users.router.ts":"2023-04-11T11:53:49.166Z","functions/src/users/users.controller.ts":"2023-04-11T11:53:49.166Z","functions/src/users/users.service.ts":"2023-04-11T11:53:49.166Z","functions/src/users/users.dto.ts":"2023-04-11T11:53:49.166Z","functions/src/users/users.entity.ts":"2023-04-11T11:53:49.166Z","functions/src/common/interfaces/userflow.ts":"2023-04-11T11:53:49.160Z","functions/src/common/interfaces/baseRoute.interface.ts":"2023-04-11T11:53:49.160Z","functions/src/common/interfaces/requestUser.interface.ts":"2023-04-11T11:53:49.160Z","functions/src/common/base/repository.base.ts":"2023-04-11T11:53:49.159Z","functions/src/common/helpers/validator.helper.ts":"2023-04-11T11:53:49.160Z","functions/src/common/errors/general.error.ts":"2023-04-11T11:53:49.160Z","functions/src/common/errors/DB.error.ts":"2023-04-11T11:53:49.159Z","functions/src/common/utils/index.ts":"2023-04-11T11:53:49.161Z","functions/src/common/middlewares/currentEvent.middleware.ts":"2023-04-11T11:53:49.160Z","functions/src/common/middlewares/errorHandler.middleware.ts":"2023-04-11T11:53:49.160Z","functions/src/common/middlewares/fbAuth.middleware.ts":"2023-04-11T11:53:49.160Z","functions/src/common/enums/errorCode.enum.ts":"2023-04-11T11:53:49.159Z","functions/src/common/enums/guestStatus.enum.ts":"2023-04-11T11:53:49.159Z","functions/src/common/enums/packages.enum.ts":"2023-04-11T11:53:49.159Z","functions/src/common/abstract/dto.abstract.ts":"2023-04-11T11:53:49.159Z","functions/src/common/abstract/route.absrtact.ts":"2023-04-11T11:53:49.159Z","functions/src/common/abstract/entity.abstract.ts":"2023-04-11T11:53:49.159Z","functions/src/indexDev.ts":"2023-04-11T12:14:46.437Z","functions/src/taskManager/tasks.entity.ts":"2023-04-11T11:53:49.165Z","functions/src/taskManager/tasks.controller.ts":"2023-04-11T11:53:49.165Z","functions/src/taskManager/tasks.dto.ts":"2023-04-11T11:53:49.165Z","functions/src/taskManager/tasks.service.ts":"2023-04-11T11:53:49.166Z","functions/src/taskManager/tasks.router.ts":"2023-04-11T11:53:49.166Z","functions/src/taskManager/tasks.repository.ts":"2023-04-11T11:53:49.165Z","functions/src/tables/tables.controller.ts":"2023-04-11T11:53:49.164Z","functions/src/tables/tables.service.ts":"2023-04-11T11:53:49.165Z","functions/src/tables/tables.entity.ts":"2023-04-11T11:53:49.165Z","functions/src/tables/tables.repository.ts":"2023-04-11T11:53:49.165Z","functions/src/tables/tables.dto.ts":"2023-04-11T11:53:49.164Z","functions/src/tables/tables.router.ts":"2023-04-11T11:53:49.165Z","functions/src/guestCategories/guestCategories.respository.ts":"2023-04-11T11:53:49.163Z","functions/src/guestCategories/GuestsCategory.service.ts":"2023-04-11T11:53:49.163Z","functions/src/guestCategories/guestCategories.router.ts":"2023-04-11T11:53:49.163Z","functions/src/guestCategories/guestCategories.controller.ts":"2023-04-11T11:53:49.163Z","functions/src/guestCategories/guestCategories.entity.ts":"2023-04-11T11:53:49.163Z","functions/src/indexTest.ts":"2023-04-12T22:01:42.670Z"}}